setup.py
serializers/__init__.py
serializers/consts.py
serializers/factory.py
serializers/packing_tool.py
serializers/serializer.py
serializers/serializer_json.py
serializers/serializer_xml.py
serializers_for_lab3.egg-info/PKG-INFO
serializers_for_lab3.egg-info/SOURCES.txt
serializers_for_lab3.egg-info/dependency_links.txt
serializers_for_lab3.egg-info/requires.txt
serializers_for_lab3.egg-info/top_level.txt