Metadata-Version: 2.1
Name: serializers-for-lab3
Version: 0.1.1
Summary: Library for python serialization & deserialization in Json & Xml
Home-page: https://github.com/Shakuriks/IgiLabs/tree/lab3
Author: Legonkov Nikita
Author-email: legonkovnikita77@gmail.com
License: MIT
Classifier: Intended Audience :: Developers
Classifier: Programming Language :: Python :: 3.10
Classifier: Operating System :: OS Independent
